src/__init__.py
my_project_0880_10-0.0.1.dist-info/LICENSE
my_project_0880_10-0.0.1.dist-info/METADATA
my_project_0880_10-0.0.1.dist-info/WHEEL
my_project_0880_10-0.0.1.dist-info/top_level.txt
my_project_0880_10-0.0.1.dist-info/RECORD
