Metadata-Version: 2.1
Name: my-project-0880-10
Version: 0.0.1
Author-email: Mark Mayerfeld <nosanmark@gmail.com>
License: MIT License
Project-URL: documentation, https://readthedocs.org
Project-URL: repository, https://github.com/RakitaLabSoftware/rlsmorph
Project-URL: changelog, https://github.com/me/spam/blob/master/CHANGELOG.md
Requires-Python: >=3.11
License-File: LICENSE
Requires-Dist: numpy
Provides-Extra: dev
Requires-Dist: pytest ; extra == 'dev'
Requires-Dist: black ; extra == 'dev'
Requires-Dist: isort ; extra == 'dev'
Requires-Dist: build ; extra == 'dev'
